copairs/__init__.py
copairs/compute.py
copairs/matching.py
copairs/plot.py
copairs/replicating.py
copairs/map/__init__.py
copairs/map/average_precision.py
copairs/map/filter.py
copairs/map/map.py
copairs/map/multilabel.py
copairs/map/normalization.py
copairs-0.5.3.dist-info/licenses/LICENSE
copairs-0.5.3.dist-info/METADATA
copairs-0.5.3.dist-info/WHEEL
copairs-0.5.3.dist-info/top_level.txt
copairs-0.5.3.dist-info/RECORD
