Metadata-Version: 2.4
Name: copairs
Version: 0.5.3
Summary: Find pairs and compute metrics between them
Author-email: John Arevalo <johnarevalo@gmail.com>, Alexandr Kalinin <akalinin@broadinstitute.org>, "Alan F. Munoz" <amunozgo@broadinstitute.org>
Project-URL: Homepage, https://github.com/cytomining/copairs
Project-URL: Bug Reports, https://github.com/cytomining/copairs/issues
Project-URL: Source, https://github.com/cytomining/copairs/
Keywords: pairwise,replication
Requires-Python: <3.13,>=3.9
License-File: LICENSE
Requires-Dist: pandas
Requires-Dist: tqdm
Requires-Dist: statsmodels
Requires-Dist: duckdb>=1.4.0
Provides-Extra: dev
Requires-Dist: jupyter>=1.1.1; extra == "dev"
Requires-Dist: pytest>=8.3.4; extra == "dev"
Requires-Dist: ruff; extra == "dev"
Requires-Dist: scikit-learn>=1.3.2; extra == "dev"
Provides-Extra: test
Requires-Dist: pytest>=8.3.4; extra == "test"
Requires-Dist: scikit-learn>=1.3.2; extra == "test"
Provides-Extra: plot
Requires-Dist: plotly; extra == "plot"
Provides-Extra: demo
Requires-Dist: notebook; extra == "demo"
Requires-Dist: matplotlib; extra == "demo"
Provides-Extra: docs
Requires-Dist: mkdocs; extra == "docs"
Requires-Dist: mkdocs-material; extra == "docs"
Requires-Dist: mkdocstrings[python]>=0.29.1; extra == "docs"
Requires-Dist: mkdocs-section-index; extra == "docs"
Requires-Dist: mkdocs-jupyter; extra == "docs"
Dynamic: license-file
